pgnn/__init__.py
pgnn/featurizers/__init__.py
pgnn/featurizers/megnet_models.py
pgnn/featurizers/structure.py
pgnn/featurizers/custom_models/MEGNetModel__MatMinerEncoded_v1.h5
pgnn/featurizers/custom_models/MEGNetModel__MatMinerEncoded_v1_scaler.pkl
pgnn/featurizers/custom_models/MEGNetModel__OFMEncoded_v1.h5
pgnn/featurizers/custom_models/MEGNetModel__OFMEncoded_v1_scaler.pkl
pgnn-0.1.0.dist-info/METADATA
pgnn-0.1.0.dist-info/WHEEL
pgnn-0.1.0.dist-info/top_level.txt
pgnn-0.1.0.dist-info/RECORD
