Metadata-Version: 2.1
Name: pgnn
Version: 0.1.0
Summary: A package that uses pretrained graph-neural network models as featurizers for materials structures.
Home-page: https://github.com/rogeriog/pGNN
Author: Rogério A. Gouvêa
Author-email: rogeriog.em@gmail.com
License: MIT License
Classifier: Programming Language :: Python :: 3
Classifier: License :: OSI Approved :: MIT License
Classifier: Operating System :: OS Independent
Requires-Python: >=3.8
Requires-Dist: tensorflow (>=2.0)
Requires-Dist: scikit-learn (>=0.24.0)
Requires-Dist: h5py (>=2.10.0)
Requires-Dist: pandas (>=1.1.0)
Requires-Dist: numpy (>=1.18.0)
Requires-Dist: megnet (>=1.0.0)
Requires-Dist: keras (>=2.3.0)
Requires-Dist: contextlib2
Requires-Dist: pickle-mixin
Requires-Dist: pymatgen (>=2022.0.0)
